correos_seguimiento/__init__.py
correos_seguimiento/errors.py
correos_seguimiento/responses/__init__.py
correos_seguimiento/responses/shipment.py
correos_seguimiento/services/__init__.py
correos_seguimiento/services/shipment.py
correos_seguimiento-0.3.0.dist-info/METADATA
correos_seguimiento-0.3.0.dist-info/WHEEL
correos_seguimiento-0.3.0.dist-info/top_level.txt
correos_seguimiento-0.3.0.dist-info/RECORD
