Metadata-Version: 2.1
Name: correos-seguimiento
Version: 0.3.0
Summary: Python wrapper for Correos Seguimiento JSON API
Home-page: https://git.coopdevs.org/coopdevs/som-connexio/correos/correos-seguimiento
Author: Coopdevs, Som Connexio
Author-email: info@coopdevs.org
Maintainer: Daniel Palomar, Gerard Funosas, César López
License: UNKNOWN
Platform: UNKNOWN
Classifier: Development Status :: 5 - Production/Stable
Classifier: Operating System :: POSIX :: Linux
Classifier: Programming Language :: Python :: 3
Classifier: Programming Language :: Python :: 3.7
Requires-Dist: requests
